fakturownia/__init__.py
fakturownia/base.py
fakturownia/cli.py
fakturownia/core.py
fakturownia/endpoints.py
fakturownia/exceptions.py
fakturownia/factories.py
fakturownia/settings.py
fakturownia/vat.py
fakturownia-0.2.2.dist-info/DESCRIPTION.rst
fakturownia-0.2.2.dist-info/METADATA
fakturownia-0.2.2.dist-info/RECORD
fakturownia-0.2.2.dist-info/WHEEL
fakturownia-0.2.2.dist-info/entry_points.txt
fakturownia-0.2.2.dist-info/metadata.json
fakturownia-0.2.2.dist-info/top_level.txt
