Metadata-Version: 2.0
Name: fakturownia
Version: 0.2.2
Summary: Python client library for the Fakturownia API
Home-page: https://github.com/wooyek/fakturownia-python
Author: Janusz Skonieczny
Author-email: js+pypi@bravelabs.pl
License: MIT license
Keywords: fakturownia-python
Platform: UNKNOWN
Classifier: Development Status :: 2 - Pre-Alpha
Classifier: Intended Audience :: Developers
Classifier: License :: OSI Approved :: MIT License
Classifier: Natural Language :: English
Classifier: Programming Language :: Python :: 2
Classifier: Programming Language :: Python :: 2.7
Classifier: Programming Language :: Python :: 3
Classifier: Programming Language :: Python :: 3.4
Classifier: Programming Language :: Python :: 3.5
Classifier: Programming Language :: Python :: 3.6
Classifier: Programming Language :: Python :: 3.7
Requires-Python: >=2.7
Requires-Dist: six
Requires-Dist: click
Requires-Dist: envparse
Requires-Dist: requests
Requires-Dist: pathlib; python_version < "3.3"
Requires-Dist: pathlib2; python_version < "3.3"
Requires-Dist: enum34; python_version < "3.4"
Provides-Extra: factories
Requires-Dist: factory-boy; extra == 'factories'
